odoo/addons/l10n_th_mis_report/README.rst
odoo/addons/l10n_th_mis_report/__init__.py
odoo/addons/l10n_th_mis_report/__manifest__.py
odoo/addons/l10n_th_mis_report/data/mis_report_bs.xml
odoo/addons/l10n_th_mis_report/data/mis_report_pl.xml
odoo/addons/l10n_th_mis_report/data/mis_report_style.xml
odoo/addons/l10n_th_mis_report/data/mis_report_tb.xml
odoo/addons/l10n_th_mis_report/i18n/l10n_th_mis_report.pot
odoo/addons/l10n_th_mis_report/readme/CONTRIBUTORS.md
odoo/addons/l10n_th_mis_report/readme/DESCRIPTION.md
odoo/addons/l10n_th_mis_report/static/description/icon.png
odoo/addons/l10n_th_mis_report/static/description/index.html
odoo_addon_l10n_th_mis_report-18.0.1.0.0.3.dist-info/METADATA
odoo_addon_l10n_th_mis_report-18.0.1.0.0.3.dist-info/WHEEL
odoo_addon_l10n_th_mis_report-18.0.1.0.0.3.dist-info/top_level.txt
odoo_addon_l10n_th_mis_report-18.0.1.0.0.3.dist-info/RECORD
